mecache/__init__.py
mecache/__version__.py
mecache/_aiofile.py
mecache/_aioredis.py
mecache/_file.py
mecache/_memory.py
mecache/_redis.py
mecache/core.py
mecache-1.4.2.dist-info/LICENSE
mecache-1.4.2.dist-info/METADATA
mecache-1.4.2.dist-info/WHEEL
mecache-1.4.2.dist-info/top_level.txt
mecache-1.4.2.dist-info/RECORD
