Metadata-Version: 2.1
Name: mecache
Version: 1.4.2
Summary: An easy-to-use cache module
Home-page: https://github.com/AberSheeran/mecache
Author: AberSheeran
Author-email: AberSheeran@outlook.com
License: MIT
Keywords: cache,redis,file,python,asyncio,aiocache
Platform: UNKNOWN
Classifier: License :: OSI Approved :: MIT License
Classifier: Programming Language :: Python :: 3.6
Requires-Python: >=3.6.0
Provides-Extra: aiofile
Requires-Dist: aiofiles ; extra == 'aiofile'
Provides-Extra: aioredis
Requires-Dist: aioredis ; extra == 'aioredis'
Provides-Extra: redis
Requires-Dist: redis ; extra == 'redis'
